django_excel/__init__.py
django_excel/_compact.py
django_excel-0.0.10.dist-info/DESCRIPTION.rst
django_excel-0.0.10.dist-info/METADATA
django_excel-0.0.10.dist-info/RECORD
django_excel-0.0.10.dist-info/WHEEL
django_excel-0.0.10.dist-info/metadata.json
django_excel-0.0.10.dist-info/top_level.txt
mysite/__init__.py
mysite/settings.py
mysite/urls.py
mysite/wsgi.py
polls/__init__.py
polls/admin.py
polls/models.py
polls/urls.py
polls/views.py
